guten/__init__.py
guten/__main__.py
guten/backend.py
guten/backends/html.py
guten/backends/text.py
guten/config.py
guten/filters.py
guten/metadata.py
guten/press.py
guten/source.py
guten/utils.py
guten-0.3.0.dist-info/METADATA
guten-0.3.0.dist-info/WHEEL
guten-0.3.0.dist-info/RECORD
