Metadata-Version: 2.1
Name: guten
Version: 0.3.0
Summary: 
Author: Elton
Author-email: eltonp3103@gmail.com
Requires-Python: >=3.8,<4.0
Classifier: Programming Language :: Python :: 3
Classifier: Programming Language :: Python :: 3.8
Classifier: Programming Language :: Python :: 3.9
Classifier: Programming Language :: Python :: 3.10
Classifier: Programming Language :: Python :: 3.11
Classifier: Programming Language :: Python :: 3.12
Requires-Dist: feedparser (>=6.0.10,<7.0.0)
Requires-Dist: httpx (>=0.23.1,<0.24.0)
Requires-Dist: numpy (>=1.26.4,<2.0.0)
Requires-Dist: pandas (>=1.5.2,<2.0.0)
Requires-Dist: python-dateutil (>=2.8.2,<3.0.0)
Requires-Dist: pytz (>=2022.7,<2023.0)
Requires-Dist: toml (==0.10.2)
